<?xml version="1.0" encoding="utf-8"?>
<FHYResultOfFHYCityData xmlns:xsd="http://www.w3.org/2001/XMLSchema" xmlns:xsi="http://www.w3.org/2001/XMLSchema-instance" xmlns="https://tempuri.org/">
  <UpdataTime>2023-04-17T03:53:01</UpdataTime>
  <Data>
    <FHYCityData>
      <Code>10008</Code>
      <Name>
        <zh_TW>南投縣</zh_TW>
        <En>NantouCounty</En>
      </Name>
    </FHYCityData>
    <FHYCityData>
      <Code>09007</Code>
      <Name>
        <zh_TW>連江縣</zh_TW>
        <En>LienchiangCounty</En>
      </Name>
    </FHYCityData>
    <FHYCityData>
      <Code>10005</Code>
      <Name>
        <zh_TW>苗栗縣</zh_TW>
        <En>MiaoliCounty</En>
      </Name>
    </FHYCityData>
    <FHYCityData>
      <Code>10017</Code>
      <Name>
        <zh_TW>基隆市</zh_TW>
        <En>Keelung</En>
      </Name>
    </FHYCityData>
    <FHYCityData>
      <Code>10020</Code>
      <Name>
        <zh_TW>嘉義市</zh_TW>
        <En>Chiayi</En>
      </Name>
    </FHYCityData>
    <FHYCityData>
      <Code>10004</Code>
      <Name>
        <zh_TW>新竹縣</zh_TW>
        <En>HsinchuCounty</En>
      </Name>
    </FHYCityData>
    <FHYCityData>
      <Code>10016</Code>
      <Name>
        <zh_TW>澎湖縣</zh_TW>
        <En>PenghuCounty</En>
      </Name>
    </FHYCityData>
    <FHYCityData>
      <Code>65</Code>
      <Name>
        <zh_TW>新北市</zh_TW>
        <En>NewTaipei</En>
      </Name>
    </FHYCityData>
    <FHYCityData>
      <Code>10009</Code>
      <Name>
        <zh_TW>雲林縣</zh_TW>
        <En>YunlinCounty</En>
      </Name>
    </FHYCityData>
    <FHYCityData>
      <Code>66</Code>
      <Name>
        <zh_TW>臺中市</zh_TW>
        <En>Taichung</En>
      </Name>
    </FHYCityData>
    <FHYCityData>
      <Code>10013</Code>
      <Name>
        <zh_TW>屏東縣</zh_TW>
        <En>PingtungCounty</En>
      </Name>
    </FHYCityData>
    <FHYCityData>
      <Code>67</Code>
      <Name>
        <zh_TW>臺南市</zh_TW>
        <En>Tainan</En>
      </Name>
    </FHYCityData>
    <FHYCityData>
      <Code>10018</Code>
      <Name>
        <zh_TW>新竹市</zh_TW>
        <En>Hsinchu</En>
      </Name>
    </FHYCityData>
    <FHYCityData>
      <Code>10014</Code>
      <Name>
        <zh_TW>臺東縣</zh_TW>
        <En>TaitungCounty</En>
      </Name>
    </FHYCityData>
    <FHYCityData>
      <Code>10002</Code>
      <Name>
        <zh_TW>宜蘭縣</zh_TW>
        <En>YilanCounty</En>
      </Name>
    </FHYCityData>
    <FHYCityData>
      <Code>10010</Code>
      <Name>
        <zh_TW>嘉義縣</zh_TW>
        <En>ChiayiCounty</En>
      </Name>
    </FHYCityData>
    <FHYCityData>
      <Code>64</Code>
      <Name>
        <zh_TW>高雄市</zh_TW>
        <En>Kaohsiung</En>
      </Name>
    </FHYCityData>
    <FHYCityData>
      <Code>63</Code>
      <Name>
        <zh_TW>臺北市</zh_TW>
        <En>Taipei</En>
      </Name>
    </FHYCityData>
    <FHYCityData>
      <Code>10015</Code>
      <Name>
        <zh_TW>花蓮縣</zh_TW>
        <En>HualienCounty</En>
      </Name>
    </FHYCityData>
    <FHYCityData>
      <Code>10007</Code>
      <Name>
        <zh_TW>彰化縣</zh_TW>
        <En>ChanghuaCounty</En>
      </Name>
    </FHYCityData>
    <FHYCityData>
      <Code>09020</Code>
      <Name>
        <zh_TW>金門縣</zh_TW>
        <En>KinmenCounty</En>
      </Name>
    </FHYCityData>
    <FHYCityData>
      <Code>68</Code>
      <Name>
        <zh_TW>桃園市</zh_TW>
        <En>Taoyuan</En>
      </Name>
    </FHYCityData>
  </Data>
</FHYResultOfFHYCityData>